mongo_utilities/__init__.py
mongo_utilities/mongo_utilities.py
mongo_utilities-0.1.4.dist-info/METADATA
mongo_utilities-0.1.4.dist-info/WHEEL
mongo_utilities-0.1.4.dist-info/top_level.txt
mongo_utilities-0.1.4.dist-info/RECORD
