Metadata-Version: 2.1
Name: mongo-utilities
Version: 0.1.4
Summary: library that simplifies MongoDB operations
Author: ABED ALWAHAB ALKHANJI
Author-email: a.w.khanji@hotmail.com
Platform: Any
Requires-Dist: pymongo
Requires-Dist: mongoengine
